seleniumprocessor/__init__.py
seleniumprocessor-0.1.5.dist-info/METADATA
seleniumprocessor-0.1.5.dist-info/WHEEL
seleniumprocessor-0.1.5.dist-info/top_level.txt
seleniumprocessor-0.1.5.dist-info/RECORD
