Metadata-Version: 2.1
Name: seleniumprocessor
Version: 0.1.5
Summary: A simple library to set up Selenium processes
Home-page: https://github.com/auino/seleniumprocessor
Author: Enrico Cambiaso
Author-email: enrico.cambiaso@gmail.com
License: UNKNOWN
Platform: UNKNOWN
Classifier: Programming Language :: Python :: 3
Classifier: License :: OSI Approved :: MIT License
Classifier: Operating System :: OS Independent
Requires-Python: >=3.6
